lassonet/__init__.py
lassonet/cox.py
lassonet/interfaces.py
lassonet/model.py
lassonet/plot.py
lassonet/prox.py
lassonet/r.py
lassonet/utils.py
lassonet-0.0.20.dist-info/LICENSE
lassonet-0.0.20.dist-info/METADATA
lassonet-0.0.20.dist-info/WHEEL
lassonet-0.0.20.dist-info/top_level.txt
lassonet-0.0.20.dist-info/RECORD
