Metadata-Version: 2.1
Name: lassonet
Version: 0.0.20
Summary: Reference implementation of LassoNet
Home-page: https://github.com/lasso-net/lassonet
Author: Louis Abraham, Ismael Lemhadri
Author-email: louis.abraham@yahoo.fr, lemhadri@stanford.edu
License: MIT
Classifier: Programming Language :: Python :: 3
Classifier: License :: OSI Approved :: MIT License
Classifier: Topic :: Scientific/Engineering :: Artificial Intelligence
Classifier: Operating System :: OS Independent
Requires-Python: >=3.8
License-File: LICENSE
Requires-Dist: torch>=1.11
Requires-Dist: scikit-learn
Requires-Dist: matplotlib
Requires-Dist: sortedcontainers
Requires-Dist: tqdm
Provides-Extra: dev
Requires-Dist: pre-commit; extra == "dev"
Requires-Dist: sphinx; extra == "dev"
Requires-Dist: black; extra == "dev"
